ringdb/DataFrameClasses.py
ringdb/Database.py
ringdb/File.py
ringdb/PosteriorDatabase.py
ringdb/StrainDatabase.py
ringdb/__init__.py
ringdb/peak.py
ringdb/metadb/__init__.py
ringdb/metadb/posterior_urls.csv
ringdb/metadb/psd_urls.csv
ringdb/metadb/strain_urls.csv
ringdb-0.1.3.5.dist-info/LICENSE
ringdb-0.1.3.5.dist-info/METADATA
ringdb-0.1.3.5.dist-info/WHEEL
ringdb-0.1.3.5.dist-info/top_level.txt
ringdb-0.1.3.5.dist-info/RECORD
