Metadata-Version: 2.1
Name: ringdb
Version: 0.1.3.5
Home-page: https://github.com/potatoasad/ringdb
Download-URL: https://github.com/Potatoasad/ringdb/archive/refs/tags/v0.1.3.5.zip
Author: Asad Hussain
Author-email: asadh@utexas.edu
License: MIT
License-File: LICENSE
Requires-Dist: h5py
Requires-Dist: matplotlib
Requires-Dist: numpy
Requires-Dist: pandas
Requires-Dist: tqdm
